bsdatetime/__init__.py
bsdatetime/bs_lookup.py
bsdatetime/config.py
bsdatetime/conversion.py
bsdatetime/formatting.py
bsdatetime/utils.py
bsdatetime/validation.py
bsdatetime/data/calendar_bs.csv
bsdatetime-1.0.1.dist-info/licenses/LICENSE
bsdatetime-1.0.1.dist-info/METADATA
bsdatetime-1.0.1.dist-info/WHEEL
bsdatetime-1.0.1.dist-info/top_level.txt
bsdatetime-1.0.1.dist-info/RECORD
