Metadata-Version: 2.4
Name: bsdatetime
Version: 1.0.1
Summary: Bikram Sambat (Nepali) date/datetime conversion and utilities
Home-page: https://github.com/Rajendra-Katuwal/bsdatetime
Author: Rajendra Katuwal
Author-email: Rajendra Katuwal <raj.katuwal2061@gmail.com>
License: MIT
Project-URL: Homepage, https://github.com/Rajendra-Katuwal/bsdatetime
Project-URL: Documentation, https://rajendra-katuwal.github.io/bsdatetime.docs/
Project-URL: Issues, https://github.com/Rajendra-Katuwal/bsdatetime/issues
Project-URL: Source, https://github.com/Rajendra-Katuwal/bsdatetime
Keywords: bikram sambat,nepali,calendar,date,datetime,conversion
Classifier: Intended Audience :: Developers
Classifier: Topic :: Software Development :: Internationalization
Classifier: Topic :: Software Development :: Libraries :: Python Modules
Classifier: Programming Language :: Python :: 3
Classifier: Programming Language :: Python :: 3.9
Classifier: Programming Language :: Python :: 3.10
Classifier: Programming Language :: Python :: 3.11
Classifier: Programming Language :: Python :: 3.12
Classifier: License :: OSI Approved :: MIT License
Classifier: Operating System :: OS Independent
Classifier: Development Status :: 5 - Production/Stable
Classifier: Topic :: Scientific/Engineering :: Information Analysis
Requires-Python: >=3.9
License-File: LICENSE
Dynamic: author
Dynamic: home-page
Dynamic: license-file
Dynamic: requires-python
